openman/__init__.py
openman/cli.py
openman/errors.py
openman/schema_converter.py
openman/utils.py
openman/mock/__init__.py
openman/mock/fakemock_resolver.py
openman/mock/mock.py
openman/parser/__init__.py
openman/parser/collection.py
openman/parser/folder.py
openman/parser/request.py
openman/parser/requestitem.py
openman/parser/response.py
openman/spec/__init__.py
openman/spec/operation.py
openman/spec/plugins.py
openman/spec/spec.py
openman/spec/collector/__init__.py
openman/spec/collector/response.py
Openman-1.2.0.dist-info/METADATA
Openman-1.2.0.dist-info/WHEEL
Openman-1.2.0.dist-info/entry_points.txt
Openman-1.2.0.dist-info/top_level.txt
Openman-1.2.0.dist-info/RECORD
